terracatalogueclient/__init__.py
terracatalogueclient/auth.py
terracatalogueclient/client.py
terracatalogueclient/config.py
terracatalogueclient/exceptions.py
terracatalogueclient/resources/cgls.ini
terracatalogueclient/resources/hrvpp.ini
terracatalogueclient/resources/terrascope.ini
terracatalogueclient-0.1.19.dist-info/LICENSE
terracatalogueclient-0.1.19.dist-info/METADATA
terracatalogueclient-0.1.19.dist-info/WHEEL
terracatalogueclient-0.1.19.dist-info/top_level.txt
terracatalogueclient-0.1.19.dist-info/RECORD
