Metadata-Version: 2.1
Name: terracatalogueclient
Version: 0.1.19
Summary: Client for the Terrascope EO catalogue
Home-page: https://github.com/VITObelgium/terracatalogueclient
Author: Stijn Caerts
Author-email: stijn.caerts@vito.be
License-File: LICENSE
Requires-Dist: requests
Requires-Dist: requests-auth ~=6.0
Requires-Dist: shapely
Requires-Dist: humanfriendly
Requires-Dist: boto3
Provides-Extra: dev
Requires-Dist: pre-commit ; extra == 'dev'
Requires-Dist: ruff ; extra == 'dev'
Provides-Extra: docs
Requires-Dist: sphinx ; extra == 'docs'
Requires-Dist: sphinx-autodoc-typehints ; extra == 'docs'
